lab7/CalculadoraProg/ula.vhd
library ieee;
use ieee.std_logic_1164.all;
use ieee.numeric_std.all;

entity ula is
    port ( x,y : in signed(15 downto 0);
        op: in unsigned(2 downto 0);
        result: out unsigned(15 downto 0)
    );
end entity;

architecture a_ula of ula is
    signal tmp: signed(31 downto 0);
begin
    tmp <= x*y;
    result <=   unsigned(x + y) when op="000" else -- Soma
    unsigned(x - y) when op="001" else -- Subtração
    unsigned(tmp(15 downto 0)) when op="010" else -- Multiplicação
                "0000000000000001" when op="011" AND x=y else -- X igual a y
                "0000000000000001" when op="100" AND x>y else -- X maior que y
                "0000000000000001" when op="101" AND x(15)='1' else -- X negativo
                "0000000000000000";
end architecture;

lab7/CalculadoraProg/mux16x8.vhd
library ieee;
use ieee.std_logic_1164.all;
use ieee.numeric_std.all;

entity mux16x8 is
    port (
        sel: in unsigned(2 downto 0); -- Selection signal
        in_0, in_1, in_2, in_3, in_4, in_5, in_6, in_7: in unsigned(15 downto 0); -- Inputs
        out_sel: out unsigned(15 downto 0) -- Output
    );
end entity;

architecture a_mux16x8 of mux16x8 is

begin
    out_sel <=
    in_0 when sel = "000" else
    in_1 when sel = "001" else
    in_2 when sel = "010" else
    in_3 when sel = "011" else
    in_4 when sel = "100" else
    in_5 when sel = "101" else
    in_6 when sel = "110" else
    in_7 when sel = "111" else
    "0000000000000000";
end architecture;

lab7/CalculadoraProg/reg16bits.vhd
library ieee;
use ieee.std_logic_1164.all;
use ieee.numeric_std.all;

entity reg16bits is
    port(
        clk: in std_logic;
        rst: in std_logic;
        wr_en: in std_logic;
        data_in : in unsigned(15 downto 0);
        data_out : out unsigned(15 downto 0)
    );
end entity;

architecture a_reg16bits of reg16bits is
    signal data: unsigned(15 downto 0);
begin
    process(clk, rst, wr_en)
    begin
        if rst='1' then
            data <= "0000000000000000";
        elsif wr_en='1' then
            if rising_edge(clk) then
                data <= data_in;
            end if;
        end if;
    end process;
    
    data_out <= data;
end architecture;

lab7/CalculadoraProg/bancoReg.vhd
library ieee;
use ieee.std_logic_1164.all;
use ieee.numeric_std.all;

entity bancoReg is
    port (
        clk         : in  std_logic; -- clock
        rst         : in  std_logic; -- reset flag
        wr_en       : in  std_logic; -- write enable flag
        r_reg_0     : in  unsigned(2 downto 0); -- address of reg for r_data_0
        r_reg_1     : in  unsigned(2 downto 0); -- address of reg for r_data_0
        w_data      : in  unsigned(15 downto 0); -- data to write to reg in address w_reg
        w_reg       : in  unsigned(2 downto 0); -- address to the reg where the data will be written
        r_data_0    : out unsigned(15 downto 0); -- data of the selected reg by r_reg_0
        r_data_1    : out unsigned(15 downto 0) -- data of the selected reg by r_reg_1
    );
end;

architecture a_bancoReg of bancoReg is
    component mux16x8 is
        port(
            sel     : IN unsigned (2 downto 0);
            in_0    : IN unsigned (15 downto 0);
            in_1    : IN unsigned (15 downto 0);
            in_2    : IN unsigned (15 downto 0);
            in_3    : IN unsigned (15 downto 0);
            in_4    : IN unsigned (15 downto 0);
            in_5    : IN unsigned (15 downto 0);
            in_6    : IN unsigned (15 downto 0);
            in_7    : IN unsigned (15 downto 0);
            out_sel : OUT unsigned (15 downto 0)
        );
    end component;
    component reg16bits is
        port(
            clk: IN std_logic;
            rst: IN std_logic;
            wr_en: IN std_logic;
            data_in: IN unsigned (15 downto 0);
            data_out: OUT unsigned (15 downto 0)
        );
    end component;
    
    signal w_en_1, w_en_2, w_en_3, w_en_4, w_en_5, w_en_6, w_en_7: std_logic:='0';
    signal data_1, data_2, data_3, data_4, data_5, data_6, data_7: unsigned (15 downto 0);
    constant data_0: unsigned(15 downto 0) := "0000000000000000";
    
begin
    -- Definition of registers
    reg_1: reg16bits port map (clk => clk, rst => rst, wr_en => w_en_1, data_in => w_data, data_out => data_1);
    reg_2: reg16bits port map (clk => clk, rst => rst, wr_en => w_en_2, data_in => w_data, data_out => data_2);
    reg_3: reg16bits port map (clk => clk, rst => rst, wr_en => w_en_3, data_in => w_data, data_out => data_3);
    reg_4: reg16bits port map (clk => clk, rst => rst, wr_en => w_en_4, data_in => w_data, data_out => data_4);
    reg_5: reg16bits port map (clk => clk, rst => rst, wr_en => w_en_5, data_in => w_data, data_out => data_5);
    reg_6: reg16bits port map (clk => clk, rst => rst, wr_en => w_en_6, data_in => w_data, data_out => data_6);
    reg_7: reg16bits port map (clk => clk, rst => rst, wr_en => w_en_7, data_in => w_data, data_out => data_7);
    -- Output 0 MUX (r_data_0)
    mux_out_0: mux16x8 port map (sel => r_reg_0, out_sel => r_data_0, in_0 => data_0, in_1 => data_1, in_2 => data_2, in_3 => data_3, in_4 => data_4, in_5 => data_5, in_6 => data_6, in_7 => data_7);
    -- Output 1 MUX (r_data_1)
    mux_out_1: mux16x8 port map (sel => r_reg_1, out_sel => r_data_1, in_0 => data_0, in_1 => data_1, in_2 => data_2, in_3 => data_3, in_4 => data_4, in_5 => data_5, in_6 => data_6, in_7 => data_7);
    -- Checking WR_ENABLE for each reg
    w_en_1 <= '1' when wr_en = '1' AND w_reg = "001" else '0';
    w_en_2 <= '1' when wr_en = '1' AND w_reg = "010" else '0';
    w_en_3 <= '1' when wr_en = '1' AND w_reg = "011" else '0';
    w_en_4 <= '1' when wr_en = '1' AND w_reg = "100" else '0';
    w_en_5 <= '1' when wr_en = '1' AND w_reg = "101" else '0';
    w_en_6 <= '1' when wr_en = '1' AND w_reg = "110" else '0';
    w_en_7 <= '1' when wr_en = '1' AND w_reg = "111" else '0';
end architecture;

lab7/CalculadoraProg/rom.vhd
library ieee;
use ieee.std_logic_1164.all;
use ieee.numeric_std.all;
entity rom is
    port(
        clk : in std_logic;
        endereco : in unsigned(15 downto 0);
        dado : out unsigned(14 downto 0)
    );
end entity;
architecture a_rom of rom is
    type mem is array (0 to 8533) of unsigned(14 downto 0);
    constant conteudo_rom : mem := (
        "100001100000101", -- NOP
"101001100000101", -- LDI R3, 5
"101010000001000", -- LDI R4, 8
"000001101000000", -- ADD R3, R4
"010010100110000", -- MOV R5, R3
"100010100000001", -- SUBI R5, 1
"110000000010100", -- JMP 20
"101011100000101", -- LDI R7, 5
"010001101010000", -- MOV R3, R5
"110000000000011", -- JMP 3
"101011000000101", -- LDI R6, 5
--        0 => "100001100000101", -- NOP
--        1 => "101001100000101", -- LDI R3, 5
--        2 => "101010000001000", -- LDI R4, 8
--        3 => "000001101000000", -- ADD R3, R4
--        4 => "010010100110000", -- MOV R5, R3
--        5 => "100010100000001", -- SUBI R5, 1
--        6 => "110000000010100", -- JMP 20
--        7 => "101011100000101", -- LDI R7, 5
--        20 => "010001101010000", -- MOV R3, R5
--        21 => "110000000000011", -- JMP 3
--        22 => "101011000000101", -- LDI R6, 5

        others => (others=>'0')
    );
begin
    process(clk)
    begin
        if(rising_edge(clk)) then
            dado <= conteudo_rom(to_integer(endereco));
        end if;
    end process;
end architecture;

lab7/CalculadoraProg/un_controle.vhd
library ieee;
use ieee.std_logic_1164.all;
use ieee.numeric_std.all;

entity un_controle is
    port (
        clk : in std_logic;
        rst : in std_logic;
        state: in unsigned(1 downto 0);
        instr : in unsigned(14 downto 0);
        instr_wr_en: out std_logic;
        pc_wr_en: out std_logic;
        pc_rst: out std_logic;
        jump_en: out std_logic;
        br_wr_en: out std_logic;
        ula_op: out unsigned(2 downto 0);
        ula_in_a_sel: out unsigned(1 downto 0);
        ula_in_b_sel: out unsigned(1 downto 0)
    );
end;

architecture a_un_controle of un_controle is
    signal opcode_i: unsigned(2 downto 0);
begin
    -- PC reset signal
    pc_rst <= rst;
    
    -- Slice the opcode from the instruction
    opcode_i <= instr(14 downto 12);
    
    -- Fetch & Decode states
    -- "00" => Fetch
    -- "01" => Decode
    -- "10" => Execute
    instr_wr_en <= '1' when state = "00" else '0';
    
    pc_wr_en <= '1' when state = "00" else 
                '1' when opcode_i = "110" AND state ="01" else '0';
    
    br_wr_en <= '1' when state = "10" AND opcode_i /= "110" else '0'; -- only writes on execute
    
    ula_op <= --"000" when opcode_i = "000" OR opcode_i = "010" OR opcode_i = "011" OR opcode_i = "101" else -- ADD ADIW MOV LDI
              "001" when opcode_i = "001" OR opcode_i = "100" else "000"; -- SUB SUBI
    
    ula_in_a_sel <= "00" when opcode_i /= "010" AND opcode_i /= "101" else  "01"; -- 00 -> ra | 01 -> zero
    ula_in_b_sel <= "00" when opcode_i(2) = '0' AND opcode_i(1 downto 0) /= "11" else "01"; -- 00 -> rb | 01 -> immediate

    -- Jump Instr
    jump_en <= '1' when opcode_i = "110" else '0';
    
end architecture;

lab7/CalculadoraProg/maq_estados.vhd
library ieee;
use ieee.std_logic_1164.all;
use ieee.numeric_std.all;

entity maq_estados is
    port( clk,rst: in std_logic;
        estado: out unsigned(1 downto 0)
    );
end entity;

architecture a_maq_estados of maq_estados is
    signal estado_s: unsigned(1 downto 0);
begin
    process(clk,rst)
    begin
        if rst='1' then
            estado_s <= "00";
        elsif rising_edge(clk) then
            if estado_s="10" then -- se agora esta em 2
                estado_s <= "00"; -- o prox vai voltar ao zero
            else
                estado_s <= estado_s+1; -- senao avanca
            end if;
        end if;
    end process;
    estado <= estado_s;
end architecture;

lab7/CalculadoraProg/reg15bits.vhd
library ieee;
use ieee.std_logic_1164.all;
use ieee.numeric_std.all;

entity reg15bits is
    port(
        clk: in std_logic;
        rst: in std_logic;
        wr_en: in std_logic;
        data_in : in unsigned(14 downto 0);
        data_out : out unsigned(14 downto 0)
    );
end entity;

architecture a_reg15bits of reg15bits is
    signal data: unsigned(14 downto 0);
begin
    process(clk, rst, wr_en)
    begin
        if rst='1' then
            data <= "000000000000000";
        elsif wr_en='1' then
            if rising_edge(clk) then
                data <= data_in;
            end if;
        end if;
    end process;
    
    data_out <= data;
end architecture;

lab7/CalculadoraProg/processador.vhd
library ieee;
use ieee.std_logic_1164.all;
use ieee.numeric_std.all;

entity processador is
    port(
        clk: in std_logic;
        rst: in std_logic;
        state: out unsigned(1 downto 0);
        pc_out: out unsigned(15 downto 0);
        instruction: out unsigned(14 downto 0);
        br_ra: out unsigned(15 downto 0);
        br_rb: out unsigned(15 downto 0);
        ula_out: out unsigned(15 downto 0)
    );
end entity;

architecture a_processador of processador is
    component reg16bits is
        port
        (
            clk      : IN std_logic ;
            rst      : IN std_logic ;
            wr_en    : IN std_logic ;
            data_in  : IN unsigned (15 downto 0);
            data_out : OUT unsigned (15 downto 0)
        );
    end component;
    component reg15bits is
        port
        (
            clk      : IN std_logic ;
            rst      : IN std_logic ;
            wr_en    : IN std_logic ;
            data_in  : IN unsigned (14 downto 0);
            data_out : OUT unsigned (14 downto 0)
        );
    end component;
    component rom is
        port
        (
            clk      : IN std_logic ;
            endereco : IN unsigned (15 downto 0);
            dado     : OUT unsigned (14 downto 0)
        );
    end component;
    component maq_estados is
        port
        (
            clk    : IN std_logic ;
            rst    : IN std_logic ;
            estado : OUT unsigned (1 downto 0)
        );
    end component;
    component un_controle is
        port
        (
            clk         : IN std_logic ;
            rst         : IN std_logic ;
            state       : IN unsigned (1 downto 0);
            instr       : IN unsigned (14 downto 0);
            instr_wr_en : OUT std_logic;
            pc_wr_en    : OUT std_logic ;
            pc_rst      : OUT std_logic ;
            jump_en     : OUT std_logic;
            br_wr_en    : OUT std_logic;
            ula_op      : OUT unsigned(2 downto 0);
            ula_in_a_sel: OUT unsigned(1 downto 0);
            ula_in_b_sel: OUT unsigned(1 downto 0)
        );
    end component;
    component bancoReg is
        port
        (
            clk      : IN std_logic ;
            rst      : IN std_logic ;
            wr_en    : IN std_logic ;
            r_reg_0  : IN unsigned (2 downto 0);
            r_reg_1  : IN unsigned (2 downto 0);
            w_data   : IN unsigned (15 downto 0);
            w_reg    : IN unsigned (2 downto 0);
            r_data_0 : OUT unsigned (15 downto 0);
            r_data_1 : OUT unsigned (15 downto 0)
        );
    end component;
    component ula is
        port
        (
            x      : IN signed (15 downto 0);
            y      : IN signed (15 downto 0);
            op     : IN unsigned (2 downto 0);
            result : OUT unsigned (15 downto 0)
        );
    end component;
    signal pc_data_wr: unsigned(15 downto 0) := "0000000000000000";
    signal jmp_addr: unsigned(15 downto 0) := "0000000000000000";
    signal rom_out: unsigned(14 downto 0) := "000000000000000";
    -- Control signals
    signal jump_en: std_logic := '0';
    signal pc_rst: std_logic := '0';
    signal pc_wr_en: std_logic := '0';
    signal instr_wr_en: std_logic := '0';
    -- Aux signals
    signal br_ra_sel: unsigned(2 downto 0);
    signal br_rb_sel: unsigned(2 downto 0);
    signal br_wr_en: std_logic;
    signal br_wr_data: unsigned(15 downto 0);
    signal br_wr_sel: unsigned(2 downto 0);
    signal ula_in_a: unsigned(15 downto 0);
    signal ula_in_b: unsigned(15 downto 0);
    signal ula_op: unsigned(2 downto 0):="000";
    signal ula_in_a_sel: unsigned(1 downto 0);
    signal ula_in_b_sel: unsigned(1 downto 0);
    signal instr_immediate: unsigned(15 downto 0);
begin
    pc: reg16bits
    port map
    (
        clk => clk,
        rst => pc_rst,
        wr_en => pc_wr_en,
        data_in => pc_data_wr,
        data_out => pc_out
    );
    instr_reg: reg15bits
    port map
    (
        clk => clk,
        rst => rst,
        wr_en => instr_wr_en,
        data_in => rom_out,
        data_out => instruction
    );
    m_stados: maq_estados
    port map (
        clk => clk,
        rst => rst,
        estado => state
    );
    u_controle: un_controle
    port map (
        clk => clk,
        rst => rst,
        instr => instruction,
        state => state,
        jump_en => jump_en,
        instr_wr_en => instr_wr_en,
        pc_rst => pc_rst,
        pc_wr_en => pc_wr_en,
        br_wr_en => br_wr_en,
        ula_op => ula_op,
        ula_in_a_sel => ula_in_a_sel,
        ula_in_b_sel => ula_in_b_sel
    );
    m_rom: rom
    port map
    (
        clk => clk,
        endereco => pc_out,
        dado => rom_out
    );
    banco_reg: bancoReg
    port map
    (
        clk      => clk,
        rst      => rst,
        r_reg_0  => br_ra_sel, -- OK
        r_reg_1  => br_rb_sel, -- OK
        wr_en    => br_wr_en, -- OK?
        w_data   => br_wr_data, -- OK?
        w_reg    => br_wr_sel, -- OK
        r_data_0 => br_ra,
        r_data_1 => br_rb
    );
    ula_main: ula
    port map
    (
        x      => signed(ula_in_a), -- OK
        y      => signed(ula_in_b), -- OK?
        op     => ula_op, -- OK?
        result => ula_out
    );
    
    -- Bank Regs connections
    br_ra_sel <= instruction(10 downto 8);
    br_rb_sel <= instruction(6 downto 4);
    br_wr_sel <= instruction(10 downto 8);
    br_wr_data <= ula_out;
    
    -- ULA connections
    ula_in_a <= "0000000000000000" when ula_in_a_sel = "01" else br_ra; -- 00 -> ra | 01 -> zero
    ula_in_b <= instr_immediate when ula_in_b_sel = "01" else br_rb; -- 00 -> rb | 01 -> immediate
    
    -- Completes instruction instruction immediate
    instr_immediate <= "00000000" & instruction(7 downto 0) when instruction(7) = '0' else "11111111" & instruction(7 downto 0);
    
    -- Jump address (direct)
    jmp_addr <= pc_out(15 downto 11) & instruction(10 downto 0);
    
    -- PC jump OR autosum +1 address
    pc_data_wr <= jmp_addr when jump_en = '1' AND state = "01" else  pc_out + 1; -- Chuncho?

end architecture a_processador;

lab7/CalculadoraProg/processador_tb.vhd
library ieee;
use ieee.std_logic_1164.all;
use ieee.numeric_std.all;

entity processador_tb is
end;

architecture processador_tb of processador_tb is
    component processador is
        port
        (
            clk         : IN std_logic ;
            rst         : IN std_logic ;
            state       : OUT unsigned (1 downto 0);
            pc_out      : OUT unsigned (15 downto 0);
            instruction : OUT unsigned (14 downto 0);
            br_ra       : OUT unsigned (15 downto 0);
            br_rb       : OUT unsigned (15 downto 0);
            ula_out     : OUT unsigned (15 downto 0)
        );
    end component;
    -- Clock period
    constant period_time : time := 100 ns;
    signal finished : std_logic := '0';
    signal clk : std_logic;
    -- Aux Signals
    signal rst : std_logic;
    signal pc: unsigned(15 downto 0);
    signal instruction: unsigned(14 downto 0);
    signal ra: unsigned(15 downto 0);
    signal rb: unsigned(15 downto 0);
    signal ula_out: unsigned(15 downto 0);
    signal state: unsigned(1 downto 0);
begin
    proc0: processador
    port map
    (
        clk => clk,
        rst => rst,
        pc_out => pc,
        instruction => instruction,
        br_ra => ra,
        br_rb => rb,
        ula_out => ula_out,
        state => state
    );

    
    --Total simulation time
    sim_time_proc: process
    begin
        wait for 6.0 us;
        finished <= '1';
        wait;
    end process sim_time_proc;
    
    -- Clock generation
    clk_proc: process
    begin
        while finished /= '1' loop
            clk <= '0';
            wait for period_time/2;
            clk <= '1';
            wait for period_time/2;
        end loop;
        wait;
    end process clk_proc;
    
    -- Testing signals
    process
    begin
        -- Limpa estados
        rst <= '1';
        wait for 100 ns;
        rst <= '0';
        wait;
    end process;
end architecture;

lab7/CalculadoraProg/processador_tb.vcd
$date
  Wed May 25 22:28:15 2022
$end
$version
  GHDL v0
$end
$timescale
  1 fs
$end
$scope module standard $end
$upscope $end
$scope module textio $end
$upscope $end
$scope module std_logic_1164 $end
$upscope $end
$scope module numeric_std $end
$upscope $end
$scope module processador_tb $end
$var reg 1 ! finished $end
$var reg 1 " clk $end
$var reg 1 # rst $end
$var reg 16 $ pc[15:0] $end
$var reg 15 % instruction[14:0] $end
$var reg 16 & ra[15:0] $end
$var reg 16 ' rb[15:0] $end
$var reg 16 ( ula_out[15:0] $end
$var reg 2 ) state[1:0] $end
$scope module proc0 $end
$var reg 1 * clk $end
$var reg 1 + rst $end
$var reg 2 , state[1:0] $end
$var reg 16 - pc_out[15:0] $end
$var reg 15 . instruction[14:0] $end
$var reg 16 / br_ra[15:0] $end
$var reg 16 0 br_rb[15:0] $end
$var reg 16 1 ula_out[15:0] $end
$var reg 16 2 pc_data_wr[15:0] $end
$var reg 16 3 jmp_addr[15:0] $end
$var reg 15 4 rom_out[14:0] $end
$var reg 1 5 jump_en $end
$var reg 1 6 pc_rst $end
$var reg 1 7 pc_wr_en $end
$var reg 1 8 instr_wr_en $end
$var reg 3 9 br_ra_sel[2:0] $end
$var reg 3 : br_rb_sel[2:0] $end
$var reg 1 ; br_wr_en $end
$var reg 16 < br_wr_data[15:0] $end
$var reg 3 = br_wr_sel[2:0] $end
$var reg 16 > ula_in_a[15:0] $end
$var reg 16 ? ula_in_b[15:0] $end
$var reg 3 @ ula_op[2:0] $end
$var reg 2 A ula_in_a_sel[1:0] $end
$var reg 2 B ula_in_b_sel[1:0] $end
$var reg 16 C instr_immediate[15:0] $end
$scope module pc $end
$var reg 1 D clk $end
$var reg 1 E rst $end
$var reg 1 F wr_en $end
$var reg 16 G data_in[15:0] $end
$var reg 16 H data_out[15:0] $end
$var reg 16 I data[15:0] $end
$upscope $end
$scope module instr_reg $end
$var reg 1 J clk $end
$var reg 1 K rst $end
$var reg 1 L wr_en $end
$var reg 15 M data_in[14:0] $end
$var reg 15 N data_out[14:0] $end
$var reg 15 O data[14:0] $end
$upscope $end
$scope module m_stados $end
$var reg 1 P clk $end
$var reg 1 Q rst $end
$var reg 2 R estado[1:0] $end
$var reg 2 S estado_s[1:0] $end
$upscope $end
$scope module u_controle $end
$var reg 1 T clk $end
$var reg 1 U rst $end
$var reg 2 V state[1:0] $end
$var reg 15 W instr[14:0] $end
$var reg 1 X instr_wr_en $end
$var reg 1 Y pc_wr_en $end
$var reg 1 Z pc_rst $end
$var reg 1 [ jump_en $end
$var reg 1 \ br_wr_en $end
$var reg 3 ] ula_op[2:0] $end
$var reg 2 ^ ula_in_a_sel[1:0] $end
$var reg 2 _ ula_in_b_sel[1:0] $end
$var reg 3 ` opcode_i[2:0] $end
$upscope $end
$scope module m_rom $end
$var reg 1 a clk $end
$var reg 16 b endereco[15:0] $end
$var reg 15 c dado[14:0] $end
$upscope $end
$scope module banco_reg $end
$var reg 1 d clk $end
$var reg 1 e rst $end
$var reg 1 f wr_en $end
$var reg 3 g r_reg_0[2:0] $end
$var reg 3 h r_reg_1[2:0] $end
$var reg 16 i w_data[15:0] $end
$var reg 3 j w_reg[2:0] $end
$var reg 16 k r_data_0[15:0] $end
$var reg 16 l r_data_1[15:0] $end
$var reg 1 m w_en_1 $end
$var reg 1 n w_en_2 $end
$var reg 1 o w_en_3 $end
$var reg 1 p w_en_4 $end
$var reg 1 q w_en_5 $end
$var reg 1 r w_en_6 $end
$var reg 1 s w_en_7 $end
$var reg 16 t data_1[15:0] $end
$var reg 16 u data_2[15:0] $end
$var reg 16 v data_3[15:0] $end
$var reg 16 w data_4[15:0] $end
$var reg 16 x data_5[15:0] $end
$var reg 16 y data_6[15:0] $end
$var reg 16 z data_7[15:0] $end
$scope module reg_1 $end
$var reg 1 { clk $end
$var reg 1 | rst $end
$var reg 1 } wr_en $end
$var reg 16 !" data_in[15:0] $end
$var reg 16 "" data_out[15:0] $end
$var reg 16 #" data[15:0] $end
$upscope $end
$scope module reg_2 $end
$var reg 1 $" clk $end
$var reg 1 %" rst $end
$var reg 1 &" wr_en $end
$var reg 16 '" data_in[15:0] $end
$var reg 16 (" data_out[15:0] $end
$var reg 16 )" data[15:0] $end
$upscope $end
$scope module reg_3 $end
$var reg 1 *" clk $end
$var reg 1 +" rst $end
$var reg 1 ," wr_en $end
$var reg 16 -" data_in[15:0] $end
$var reg 16 ." data_out[15:0] $end
$var reg 16 /" data[15:0] $end
$upscope $end
$scope module reg_4 $end
$var reg 1 0" clk $end
$var reg 1 1" rst $end
$var reg 1 2" wr_en $end
$var reg 16 3" data_in[15:0] $end
$var reg 16 4" data_out[15:0] $end
$var reg 16 5" data[15:0] $end
$upscope $end
$scope module reg_5 $end
$var reg 1 6" clk $end
$var reg 1 7" rst $end
$var reg 1 8" wr_en $end
$var reg 16 9" data_in[15:0] $end
$var reg 16 :" data_out[15:0] $end
$var reg 16 ;" data[15:0] $end
$upscope $end
$scope module reg_6 $end
$var reg 1 <" clk $end
$var reg 1 =" rst $end
$var reg 1 >" wr_en $end
$var reg 16 ?" data_in[15:0] $end
$var reg 16 @" data_out[15:0] $end
$var reg 16 A" data[15:0] $end
$upscope $end
$scope module reg_7 $end
$var reg 1 B" clk $end
$var reg 1 C" rst $end
$var reg 1 D" wr_en $end
$var reg 16 E" data_in[15:0] $end
$var reg 16 F" data_out[15:0] $end
$var reg 16 G" data[15:0] $end
$upscope $end
$scope module mux_out_0 $end
$var reg 3 H" sel[2:0] $end
$var reg 16 I" in_0[15:0] $end
$var reg 16 J" in_1[15:0] $end
$var reg 16 K" in_2[15:0] $end
$var reg 16 L" in_3[15:0] $end
$var reg 16 M" in_4[15:0] $end
$var reg 16 N" in_5[15:0] $end
$var reg 16 O" in_6[15:0] $end
$var reg 16 P" in_7[15:0] $end
$var reg 16 Q" out_sel[15:0] $end
$upscope $end
$scope module mux_out_1 $end
$var reg 3 R" sel[2:0] $end
$var reg 16 S" in_0[15:0] $end
$var reg 16 T" in_1[15:0] $end
$var reg 16 U" in_2[15:0] $end
$var reg 16 V" in_3[15:0] $end
$var reg 16 W" in_4[15:0] $end
$var reg 16 X" in_5[15:0] $end
$var reg 16 Y" in_6[15:0] $end
$var reg 16 Z" in_7[15:0] $end
$var reg 16 [" out_sel[15:0] $end
$upscope $end
$upscope $end
$scope module ula_main $end
$var reg 16 \" x[15:0] $end
$var reg 16 ]" y[15:0] $end
$var reg 3 ^" op[2:0] $end
$var reg 16 _" result[15:0] $end
$var reg 32 `" tmp[31:0] $end
$upscope $end
$upscope $end
$upscope $end
$enddefinitions $end
#0
0!
0"
1#
b0000000000000000 $
b000000000000000 %
b0000000000000000 &
b0000000000000000 '
b0000000000000000 (
b00 )
0*
1+
b00 ,
b0000000000000000 -
b000000000000000 .
b0000000000000000 /
b0000000000000000 0
b0000000000000000 1
b0000000000000001 2
b0000000000000000 3
bUUUUUUUUUUUUUUU 4
05
16
17
18
b000 9
b000 :
0;
b0000000000000000 <
b000 =
b0000000000000000 >
b0000000000000000 ?
b000 @
b00 A
b00 B
b0000000000000000 C
0D
1E
1F
b0000000000000001 G
b0000000000000000 H
b0000000000000000 I
0J
1K
1L
bUUUUUUUUUUUUUUU M
b000000000000000 N
b000000000000000 O
0P
1Q
b00 R
b00 S
0T
1U
b00 V
b000000000000000 W
1X
1Y
1Z
0[
0\
b000 ]
b00 ^
b00 _
b000 `
0a
b0000000000000000 b
bUUUUUUUUUUUUUUU c
0d
1e
0f
b000 g
b000 h
b0000000000000000 i
b000 j
b0000000000000000 k
b0000000000000000 l
0m
0n
0o
0p
0q
0r
0s
b0000000000000000 t
b0000000000000000 u
b0000000000000000 v
b0000000000000000 w
b0000000000000000 x
b0000000000000000 y
b0000000000000000 z
0{
1|
0}
b0000000000000000 !"
b0000000000000000 ""
b0000000000000000 #"
0$"
1%"
0&"
b0000000000000000 '"
b0000000000000000 ("
b0000000000000000 )"
0*"
1+"
0,"
b0000000000000000 -"
b0000000000000000 ."
b0000000000000000 /"
00"
11"
02"
b0000000000000000 3"
b0000000000000000 4"
b0000000000000000 5"
06"
17"
08"
b0000000000000000 9"
b0000000000000000 :"
b0000000000000000 ;"
0<"
1="
0>"
b0000000000000000 ?"
b0000000000000000 @"
b0000000000000000 A"
0B"
1C"
0D"
b0000000000000000 E"
b0000000000000000 F"
b0000000000000000 G"
b000 H"
b0000000000000000 I"
b0000000000000000 J"
b0000000000000000 K"
b0000000000000000 L"
b0000000000000000 M"
b0000000000000000 N"
b0000000000000000 O"
b0000000000000000 P"
b0000000000000000 Q"
b000 R"
b0000000000000000 S"
b0000000000000000 T"
b0000000000000000 U"
b0000000000000000 V"
b0000000000000000 W"
b0000000000000000 X"
b0000000000000000 Y"
b0000000000000000 Z"
b0000000000000000 ["
b0000000000000000 \"
b0000000000000000 ]"
b000 ^"
b0000000000000000 _"
b00000000000000000000000000000000 `"
#50000000
1"
1*
b101000111111011 4
1D
1J
b101000111111011 M
1P
1T
1a
b101000111111011 c
1d
1{
1$"
1*"
10"
16"
1<"
1B"
#100000000
0"
0#
0*
0+
06
0D
0E
0J
0K
0P
0Q
0T
0U
0Z
0a
0d
0e
0{
0|
0$"
0%"
0*"
0+"
00"
01"
06"
07"
0<"
0="
0B"
0C"
#150000000
1"
b0000000000000001 $
b101000111111011 %
b1111111111111011 (
b01 )
1*
b01 ,
b0000000000000001 -
b101000111111011 .
b1111111111111011 1
b0000000000000010 2
b0000000111111011 3
07
08
b001 9
b111 :
b1111111111111011 <
b001 =
b1111111111111011 ?
b01 A
b01 B
b1111111111111011 C
1D
0F
b0000000000000010 G
b0000000000000001 H
b0000000000000001 I
1J
0L
b101000111111011 N
b101000111111011 O
1P
b01 R
b01 S
1T
b01 V
b101000111111011 W
0X
0Y
b01 ^
b01 _
b101 `
1a
b0000000000000001 b
1d
b001 g
b111 h
b1111111111111011 i
b001 j
1{
b1111111111111011 !"
1$"
b1111111111111011 '"
1*"
b1111111111111011 -"
10"
b1111111111111011 3"
16"
b1111111111111011 9"
1<"
b1111111111111011 ?"
1B"
b1111111111111011 E"
b001 H"
b111 R"
b1111111111111011 ]"
b1111111111111011 _"
#200000000
0"
0*
0D
0J
0P
0T
0a
0d
0{
0$"
0*"
00"
06"
0<"
0B"
#250000000
1"
b10 )
1*
b10 ,
b101001011111101 4
1;
1D
1J
b101001011111101 M
1P
b10 R
b10 S
1T
b10 V
1\
1a
b101001011111101 c
1d
1f
1m
1{
1}
1$"
1*"
10"
16"
1<"
1B"
#300000000
0"
0*
0D
0J
0P
0T
0a
0d
0{
0$"
0*"
00"
06"
0<"
0B"
#350000000
1"
b1111111111111011 &
b00 )
1*
b00 ,
b1111111111111011 /
17
18
0;
1D
1F
1J
1L
1P
b00 R
b00 S
1T
b00 V
1X
1Y
0\
1a
1d
0f
b1111111111111011 k
0m
b1111111111111011 t
1{
0}
b1111111111111011 ""
b1111111111111011 #"
1$"
1*"
10"
16"
1<"
1B"
b1111111111111011 J"
b1111111111111011 Q"
b1111111111111011 T"
#400000000
0"
0*
0D
0J
0P
0T
0a
0d
0{
0$"
0*"
00"
06"
0<"
0B"
#450000000
1"
b0000000000000010 $
b101001011111101 %
b0000000000000000 &
b1111111111111101 (
b01 )
1*
b01 ,
b0000000000000010 -
b101001011111101 .
b0000000000000000 /
b1111111111111101 1
b0000000000000011 2
b0000001011111101 3
07
08
b010 9
b1111111111111101 <
b010 =
b1111111111111101 ?
b1111111111111101 C
1D
0F
b0000000000000011 G
b0000000000000010 H
b0000000000000010 I
1J
0L
b101001011111101 N
b101001011111101 O
1P
b01 R
b01 S
1T
b01 V
b101001011111101 W
0X
0Y
1a
b0000000000000010 b
1d
b010 g
b1111111111111101 i
b010 j
b0000000000000000 k
1{
b1111111111111101 !"
1$"
b1111111111111101 '"
1*"
b1111111111111101 -"
10"
b1111111111111101 3"
16"
b1111111111111101 9"
1<"
b1111111111111101 ?"
1B"
b1111111111111101 E"
b010 H"
b0000000000000000 Q"
b1111111111111101 ]"
b1111111111111101 _"
#500000000
0"
0*
0D
0J
0P
0T
0a
0d
0{
0$"
0*"
00"
06"
0<"
0B"
#550000000
1"
b10 )
1*
b10 ,
b101001111111110 4
1;
1D
1J
b101001111111110 M
1P
b10 R
b10 S
1T
b10 V
1\
1a
b101001111111110 c
1d
1f
1n
1{
1$"
1&"
1*"
10"
16"
1<"
1B"
#600000000
0"
0*
0D
0J
0P
0T
0a
0d
0{
0$"
0*"
00"
06"
0<"
0B"
#650000000
1"
b1111111111111101 &
b00 )
1*
b00 ,
b1111111111111101 /
17
18
0;
1D
1F
1J
1L
1P
b00 R
b00 S
1T
b00 V
1X
1Y
0\
1a
1d
0f
b1111111111111101 k
0n
b1111111111111101 u
1{
1$"
0&"
b1111111111111101 ("
b1111111111111101 )"
1*"
10"
16"
1<"
1B"
b1111111111111101 K"
b1111111111111101 Q"
b1111111111111101 U"
#700000000
0"
0*
0D
0J
0P
0T
0a
0d
0{
0$"
0*"
00"
06"
0<"
0B"
